{"Data":{"People":{"Rory":{"ref":"RoryCampbell","first":"Rory","last":"Campbell","location":"St. John's","birthday":"November 17th","phone":"555-5555","info":"Memorial University","schedule":{"Monday":["Buying Black TShirts","Software Design"],"Tuesday":["Web","Wearing Black TShirts"],"Wednesday":["Hanging Out With Friends","Smiling Uncontrollably"],"Thursday":["Web","Washing Black TShirts"],"Friday":["Jiu Jitsu","NLP"],"Saturday":["Who knows"],"Sunday":["Probably home"]},"friends":{"Karl":true,"John":true},"locations":{}},"John":{"ref":"JohnHollett","first":"John","last":"Hollett","location":"Conception Bay South","birthday":"May 11th","phone":"555-5555","info":"Memorial University","schedule":{"Monday":["Software Design","Help Center","Math"],"Tuesday":["Web","Help Center","Hardware"],"Wednesday":["Software Design","Help Center","Math"],"Thursday":["Web","Help Center","Hardware"],"Friday":["Software Design","Help Center","Math"],"Saturday":["Definitely Home"],"Sunday":["DEFINITELY HOME"]},"friends":{"Michael":true,"Rory":true},"locations":{}},"Michael":{"ref":"MichaelSullivan","first":"Michael","last":"Sullivan","location":"St. John's","birthday":"October 14, 1983","phone":"555-5555","info":"Memorial University","schedule":{"Monday":["Help Center","NLP"],"Tuesday":["Web","Assignments"],"Wednesday":["Help Center","Playing with Dogge"],"Thursday":["Web","Programming"],"Friday":["Help Center","NLP"],"Saturday":["Probably Sleeping"],"Sunday":["Being Michael"]},"friends":{"Rory":true},"locations":{}},"Karl":{"ref":"KarlChiasson","first":"Karl","last":"Chiasson","location":"St. John's","birthday":"March 2nd","phone":"555-5555","info":"Memorial University","schedule":{"Monday":["Software Design","Doing Things"],"Tuesday":["Web","Hardware","Ethics"],"Wednesday":["Software Design","Doing Things"],"Thursday":["Web","Hardware","Ethics"],"Friday":["Software Design","Doing Things"],"Saturday":["Playing Wow"],"Sunday":[]},"friends":{"Rory":true},"locations":{}}},"WebToKey":{"RoryCampbell":"Rory","MichaelSullivan":"Michael","KarlChiasson":"Karl","JohnHollett":"John"}}}